{
  "id": "volcano_run_extreme",
  "name": "Volcano Run: Inferno Core",
  "description": "Descend into the Inferno Core! Survive 64 zones of magma spirals, eruption escapes, lava tsunamis, and the rising lava boss caldera. Manage your heat meter, outrun 4 lava-crazed rivals, and escape the volcano before it consumes you. Heat threshold: 80. Survival rate: 2%.",
  "version": "5.0.0",
  "author": "Community Contributor - EVOLVED",
  "difficulty": "extreme",
  "zones": [
    {"type": "floor", "pos": {"x": 0, "y": -5, "z": 0}, "size": {"x": 120, "y": 1, "z": 200}, "color": [0.2, 0.1, 0.05]},
    {"type": "track", "pos": {"x": 0, "y": 5, "z": -20}, "color": [0.4, 0.2, 0.15]},
    {"type": "landing", "pos": {"x": 0, "y": 2, "z": 10}, "color": [0.5, 0.2, 0.1]},
    {"type": "checkpoint", "id": "cp_entrance", "pos": {"x": 0, "y": 3, "z": 18}, "cooling": 30, "type_checkpoint": "eruption"},
    {"type": "stairs", "pos": {"x": -20, "y": 4, "z": 25}, "steps": 10, "rise": 1.8, "color": [0.45, 0.2, 0.1], "path_id": "outer_path"},
    {"type": "stairs", "pos": {"x": 20, "y": 4, "z": 25}, "steps": 8, "rise": 2.2, "color": [0.5, 0.15, 0.08], "path_id": "inner_path", "hazard": "lava_spray"},
    {"type": "heat_zone", "pos": {"x": 20, "y": 15, "z": 32}, "intensity": 8, "path_id": "inner_path"},
    {"type": "landing", "pos": {"x": -25, "y": 22, "z": 42}, "color": [0.55, 0.25, 0.15], "path_id": "outer_path"},
    {"type": "landing", "pos": {"x": 25, "y": 18, "z": 38}, "color": [0.6, 0.2, 0.1], "path_id": "inner_path", "hazard": "lava_spray"},
    {"type": "collectible", "pos": {"x": -28, "y": 23, "z": 45}, "type_detail": "fire_gem", "value": 200, "effect": "heat_resist", "path_id": "outer_path"},
    {"type": "collectible", "pos": {"x": 28, "y": 19, "z": 40}, "type_detail": "fire_gem", "value": 300, "effect": "speed_boost", "path_id": "inner_path"},
    {"type": "bridge", "pos": {"x": -28, "y": 20, "z": 55}, "width": 4, "color": [0.5, 0.25, 0.15], "path_id": "outer_path"},
    {"type": "bridge", "pos": {"x": 28, "y": 16, "z": 50}, "width": 2, "hazards": ["lava_eruption"], "color": [0.4, 0.15, 0.08], "path_id": "inner_path"},
    {"type": "magma_spiral", "pos": {"x": -30, "y": 18, "z": 68}, "radius": 5, "rotations": 2, "descent": 8, "heat_build": 3, "path_id": "outer_path"},
    {"type": "magma_spiral", "pos": {"x": 30, "y": 14, "z": 62}, "radius": 4, "rotations": 1.5, "descent": 6, "heat_build": 4, "path_id": "inner_path"},
    {"type": "checkpoint", "id": "cp_mid", "pos": {"x": 0, "y": 10, "z": 78}, "cooling": 50, "type_checkpoint": "eruption"},
    {"type": "eruption_zone", "pos": {"x": 0, "y": 8, "z": 88}, "countdown": 8, "hazards": ["falling_rocks", "ground_crack"]},
    {"type": "bridge", "pos": {"x": -12, "y": 5, "z": 100}, "width": 3.5, "hazards": ["falling_rocks"], "color": [0.45, 0.2, 0.1], "path_id": "outer_path"},
    {"type": "bridge", "pos": {"x": 12, "y": 3, "z": 96}, "width": 2.5, "hazards": ["falling_rocks", "steam_blast"], "color": [0.35, 0.15, 0.08], "path_id": "inner_path"},
    {"type": "boost_pad", "pos": {"x": -12, "y": 5.5, "z": 108}, "type_boost": "magma_launch", "strength": 2, "path_id": "outer_path"},
    {"type": "boost_pad", "pos": {"x": 12, "y": 3.5, "z": 104}, "type_boost": "magma_dash", "strength": 2.5, "path_id": "inner_path"},
    {"type": "jump", "pos": {"x": -12, "y": 8, "z": 118}, "color": [0.6, 0.3, 0.15], "path_id": "outer_path"},
    {"type": "jump", "pos": {"x": 12, "y": 6, "z": 114}, "color": [0.65, 0.25, 0.12], "path_id": "inner_path"},
    {"type": "landing", "pos": {"x": -10, "y": 2, "z": 130}, "color": [0.5, 0.22, 0.15], "path_id": "outer_path"},
    {"type": "landing", "pos": {"x": 10, "y": 0, "z": 126}, "color": [0.55, 0.18, 0.12], "path_id": "inner_path"},
    {"type": "slalom", "pos": {"x": -8, "y": 0, "z": 145}, "obstacles": 5, "style": "rock_formations", "color": [0.5, 0.25, 0.18], "path_id": "outer_path"},
    {"type": "slalom", "pos": {"x": 8, "y": -2, "z": 140}, "obstacles": 7, "style": "volcanic_vents", "color": [0.7, 0.15, 0.1], "path_id": "inner_path"},
    {"type": "collectible", "pos": {"x": -6, "y": 1, "z": 155}, "type_detail": "obsidian_shard", "value": 150, "effect": "shield", "path_id": "outer_path"},
    {"type": "collectible", "pos": {"x": 10, "y": -1, "z": 150}, "type_detail": "obsidian_shard", "value": 200, "effect": "shield_plus_speed", "path_id": "inner_path"},
    {"type": "checkpoint", "id": "cp_final_ascent", "pos": {"x": 0, "y": -2, "z": 165}, "cooling": 60, "type_checkpoint": "eruption"},
    {"type": "stairs", "pos": {"x": 0, "y": -4, "z": 178}, "steps": 6, "rise": 1.2, "color": [0.5, 0.2, 0.15]},
    {"type": "lava_tsunami_zone", "pos": {"x": 0, "y": 0, "z": 190}, "wave_height": 5, "damage": 30, "warning_time": 8},
    {"type": "bridge", "pos": {"x": 0, "y": 3, "z": 205}, "width": 4, "hazards": ["falling_rocks"], "color": [0.45, 0.2, 0.12]},
    {"type": "collectible", "pos": {"x": 0, "y": 4, "z": 210}, "type_detail": "obsidian_shard", "value": 250, "effect": "mega_shield"},
    {"type": "eruption_zone", "pos": {"x": 0, "y": 2, "z": 220}, "countdown": 5, "hazards": ["magma_burst", "ash_cloud"]},
    {"type": "slalom", "pos": {"x": 0, "y": -1, "z": 235}, "obstacles": 8, "style": "volcanic_vents", "color": [0.7, 0.2, 0.1]},
    {"type": "collectible", "pos": {"x": -3, "y": 0, "z": 245}, "type_detail": "fire_gem", "value": 400, "effect": "mega_boost"},
    {"type": "boss_caldera", "pos": {"x": 0, "y": -3, "z": 260}, "rising_lava_rate": 0.5, "stages": 3},
    {"type": "collapsing_platform", "pos": {"x": -5, "y": 2, "z": 275}, "collapse_delay": 3, "id": "boss_platform_1"},
    {"type": "checkpoint", "pos": {"x": -5, "y": 2.5, "z": 280}, "cooling": 40, "id": "cp_boss_1"},
    {"type": "collapsing_platform", "pos": {"x": 5, "y": 5, "z": 290}, "collapse_delay": 2.5, "id": "boss_platform_2"},
    {"type": "checkpoint", "pos": {"x": 5, "y": 5.5, "z": 295}, "cooling": 40, "id": "cp_boss_2"},
    {"type": "collapsing_platform", "pos": {"x": 0, "y": 8, "z": 310}, "collapse_delay": 2, "id": "boss_platform_3"},
    {"type": "checkpoint", "pos": {"x": 0, "y": 8.5, "z": 315}, "cooling": 50, "id": "cp_boss_3"},
    {"type": "jump", "pos": {"x": 0, "y": 10, "z": 328}, "launch_angle": 40, "power": 30},
    {"type": "jump", "pos": {"x": 0, "y": 14, "z": 342}, "launch_angle": 45, "power": 35},
    {"type": "jump", "pos": {"x": 0, "y": 19, "z": 358}, "launch_angle": 50, "power": 40},
    {"type": "victory_ramp", "pos": {"x": 0, "y": 25, "z": 375}, "slope": 30},
    {"type": "goal", "pos": {"x": 0, "y": 35, "z": 395}, "color": [1, 0.1, 0]}
  ],
  "spawn": {"x": 0, "y": 10, "z": -25},
  "goals": [
    {"id": 1, "type": "checkpoint", "range": {"x": [-3, 3], "y": [2, 4], "z": [16, 20]}, "checkpoint_id": "cp_entrance"},
    {"id": 2, "type": "checkpoint", "range": {"x": [-4, 4], "y": [8, 12], "z": [76, 80]}, "checkpoint_id": "cp_mid"},
    {"id": 3, "type": "checkpoint", "range": {"x": [-3, 3], "y": [-4, 0], "z": [163, 167]}, "checkpoint_id": "cp_final_ascent"},
    {"id": 4, "type": "checkpoint", "range": {"x": [-7, -3], "y": [1, 3], "z": [278, 282]}, "checkpoint_id": "cp_boss_1"},
    {"id": 5, "type": "checkpoint", "range": {"x": [3, 7], "y": [4, 6], "z": [293, 297]}, "checkpoint_id": "cp_boss_2"},
    {"id": 6, "type": "checkpoint", "range": {"x": [-2, 2], "y": [7, 9], "z": [313, 317]}, "checkpoint_id": "cp_boss_3"},
    {"id": 7, "type": "finish", "range": {"x": [-3, 3], "y": [33, 37], "z": [393, 397]}}
  ],
  "ai_opponents": [
    {
      "id": "pyro_pete",
      "name": "Pyro Pete",
      "color": [1, 0.2, 0],
      "spawn": {"x": -1.5, "y": 10.5, "z": -25.5},
      "speed": 1.3,
      "aggression": 0.98,
      "skill": 0.9,
      "behavior": "lava_rage",
      "lava_tactics": {"push_into_hazards": true, "heat_immune": false, "lava_rage_ability": true},
      "special": "Lava Rage - speed boost when heat > 60"
    },
    {
      "id": "magma_mike",
      "name": "Magma Mike",
      "color": [0.9, 0.3, 0],
      "spawn": {"x": 1.5, "y": 10.5, "z": -25.5},
      "speed": 1.25,
      "aggression": 0.95,
      "skill": 0.92,
      "behavior": "tsunami_surfer",
      "lava_tactics": {"push_into_hazards": true, "tsunami_immune": true, "wave_riding": true},
      "special": "Tsunami Immunity - uses waves as shortcuts"
    },
    {
      "id": "ash_annie",
      "name": "Ash Annie",
      "color": [0.7, 0.7, 0.7],
      "spawn": {"x": 0, "y": 10.5, "z": -26},
      "speed": 1.2,
      "aggression": 0.9,
      "skill": 0.95,
      "behavior": "eruption_predictor",
      "lava_tactics": {"push_into_hazards": true, "eruption_prediction": true, "path_cutting": true},
      "special": "Eruption Prediction - knows safe zones before eruption"
    },
    {
      "id": "obsidian_oz",
      "name": "Obsidian Oz",
      "color": [0.15, 0.15, 0.2],
      "spawn": {"x": 2, "y": 10.5, "z": -26.5},
      "speed": 1.15,
      "aggression": 0.85,
      "skill": 0.88,
      "behavior": "platform_controller",
      "lava_tactics": {"push_into_hazards": true, "heat_resistance": 40, "platform_control": true},
      "special": "Heat Resistance - 40% slower heat buildup"
    }
  ],
  "collectibles": [
    {"id": "fire_gem_1", "type": "fire_gem", "name": "Inferno Ruby", "pos": {"x": -28, "y": 23, "z": 45}, "value": 200, "effect": "heat_resist"},
    {"id": "fire_gem_2", "type": "fire_gem", "name": "Magma Diamond", "pos": {"x": 28, "y": 19, "z": 40}, "value": 300, "effect": "speed_boost"},
    {"id": "obsidian_1", "type": "obsidian_shard", "name": "Volcanic Glass", "pos": {"x": -6, "y": 1, "z": 155}, "value": 150, "effect": "shield"},
    {"id": "obsidian_2", "type": "obsidian_shard", "name": "Crater Fragment", "pos": {"x": 10, "y": -1, "z": 150}, "value": 200, "effect": "shield_plus_speed"},
    {"id": "obsidian_3", "type": "obsidian_shard", "name": "Lava Cooled Crystal", "pos": {"x": 0, "y": 4, "z": 210}, "value": 250, "effect": "mega_shield"},
    {"id": "fire_gem_3", "type": "fire_gem", "name": "Eruption Pearl", "pos": {"x": -3, "y": 0, "z": 245}, "value": 400, "effect": "mega_boost"},
    {"id": "magma_core", "type": "legendary", "name": "Magma Core", "pos": {"x": 0, "y": 10, "z": 350}, "value": 1000, "effect": "full_cooling_invincibility"}
  ],
  "heat_system": {
    "max_heat": 100,
    "build_rate": 5,
    "damage_threshold": 80,
    "damage_rate": 10,
    "cooling_checkpoints": [30, 50, 60, 40, 40, 50],
    "overheat_effects": ["slow", "damage", "visibility_reduced"]
  },
  "hazards": {
    "falling_rocks": {"frequency": 2, "damage": 15, "warning_time": 0.7},
    "lava_pits": {"reset_on_fall": true, "instant_death": false},
    "lava_spray": {"frequency": 1.5, "damage": 20, "slow_duration": 3},
    "lava_eruption": {"frequency": 3, "damage": 30, "knockback": true},
    "steam_blast": {"frequency": 2, "push_force": 5, "warning_time": 0.5},
    "magma_burst": {"frequency": 4, "damage": 40, "aoe": true},
    "ash_cloud": {"visibility": 0.3, "duration": 5},
    "lava_tsunami": {"wave_height": 5, "damage": 30, "warning_time": 8, "creates_path": true}
  },
  "particleEffects": ["volcanic_ash", "smoke_trails", "lava_sparks", "magma_burst", "steam_puffs", "heat_shimmer"],
  "race_settings": {
    "lap_count": 1,
    "time_limit": 180,
    "rival_count": 4,
    "enable_powerups": true,
    "heat_mechanic": true,
    "scoring": {"finish_first": 2000, "finish_second": 1500, "finish_third": 1000, "collectible_bonus": true, "time_bonus": true, "heat_survival_bonus": true}
  },
  "camera": {"mode": "follow", "height": 22, "offset": -35},
  "music": "inferno_core_theme",
  "ambientSounds": ["lava_bubble", "wind_howling", "rock_crumbles", "steam_venting", "distant_eruption", "heartbeat_deep"]
}
